{
  "type": "gn",
  "code": "885729",
  "name": "参股新三板",
  "stocks": [
    {
      "code": "000735",
      "name": "罗牛山"
    },
    {
      "code": "002030",
      "name": "达安基因"
    },
    {
      "code": "300470",
      "name": "日机密封"
    },
    {
      "code": "300226",
      "name": "上海钢联"
    },
    {
      "code": "600895",
      "name": "张江高科"
    },
    {
      "code": "002624",
      "name": "完美世界"
    },
    {
      "code": "300268",
      "name": "佳沃股份"
    },
    {
      "code": "600658",
      "name": "电子城"
    },
    {
      "code": "600872",
      "name": "中炬高新"
    },
    {
      "code": "000776",
      "name": "广发证券"
    },
    {
      "code": "600171",
      "name": "上海贝岭"
    },
    {
      "code": "000728",
      "name": "国元证券"
    },
    {
      "code": "603398",
      "name": "邦宝益智"
    },
    {
      "code": "002798",
      "name": "帝欧家居"
    },
    {
      "code": "300398",
      "name": "飞凯材料"
    },
    {
      "code": "600624",
      "name": "复旦复华"
    },
    {
      "code": "000783",
      "name": "长江证券"
    },
    {
      "code": "002820",
      "name": "桂发祥"
    },
    {
      "code": "300096",
      "name": "易联众"
    },
    {
      "code": "600283",
      "name": "钱江水利"
    },
    {
      "code": "600343",
      "name": "航天动力"
    },
    {
      "code": "002711",
      "name": "欧浦智网"
    },
    {
      "code": "600363",
      "name": "联创光电"
    },
    {
      "code": "000828",
      "name": "东莞控股"
    },
    {
      "code": "002355",
      "name": "兴民智通"
    },
    {
      "code": "600064",
      "name": "南京高科"
    },
    {
      "code": "000686",
      "name": "东北证券"
    },
    {
      "code": "002174",
      "name": "游族网络"
    },
    {
      "code": "600561",
      "name": "江西长运"
    },
    {
      "code": "002634",
      "name": "棒杰股份"
    },
    {
      "code": "002673",
      "name": "西部证券"
    },
    {
      "code": "300133",
      "name": "华策影视"
    },
    {
      "code": "603007",
      "name": "花王股份"
    },
    {
      "code": "002238",
      "name": "天威视讯"
    },
    {
      "code": "601377",
      "name": "兴业证券"
    },
    {
      "code": "002067",
      "name": "景兴纸业"
    },
    {
      "code": "300192",
      "name": "科斯伍德"
    },
    {
      "code": "600133",
      "name": "东湖高新"
    },
    {
      "code": "601390",
      "name": "中国中铁"
    },
    {
      "code": "002292",
      "name": "奥飞娱乐"
    },
    {
      "code": "300227",
      "name": "光韵达"
    },
    {
      "code": "300195",
      "name": "长荣股份"
    },
    {
      "code": "600059",
      "name": "古越龙山"
    },
    {
      "code": "000931",
      "name": "中关村"
    },
    {
      "code": "002084",
      "name": "海鸥住工"
    },
    {
      "code": "000100",
      "name": "TCL集团"
    },
    {
      "code": "000628",
      "name": "高新发展"
    },
    {
      "code": "000690",
      "name": "宝新能源"
    },
    {
      "code": "000793",
      "name": "华闻传媒"
    },
    {
      "code": "600100",
      "name": "同方股份"
    },
    {
      "code": "600266",
      "name": "北京城建"
    },
    {
      "code": "600533",
      "name": "栖霞建设"
    },
    {
      "code": "601238",
      "name": "广汽集团"
    },
    {
      "code": "002307",
      "name": "北新路桥"
    },
    {
      "code": "002317",
      "name": "众生药业"
    },
    {
      "code": "002413",
      "name": "雷科防务"
    },
    {
      "code": "002783",
      "name": "凯龙股份"
    },
    {
      "code": "300126",
      "name": "锐奇股份"
    },
    {
      "code": "300356",
      "name": "光一科技"
    },
    {
      "code": "000031",
      "name": "中粮地产"
    },
    {
      "code": "000903",
      "name": "云内动力"
    },
    {
      "code": "002632",
      "name": "道明光学"
    },
    {
      "code": "002654",
      "name": "万润科技"
    },
    {
      "code": "002787",
      "name": "华源控股"
    },
    {
      "code": "300043",
      "name": "星辉娱乐"
    },
    {
      "code": "600008",
      "name": "首创股份"
    },
    {
      "code": "600103",
      "name": "青山纸业"
    },
    {
      "code": "600111",
      "name": "北方稀土"
    },
    {
      "code": "600321",
      "name": "*ST正源"
    },
    {
      "code": "603999",
      "name": "读者传媒"
    },
    {
      "code": "000516",
      "name": "国际医学"
    },
    {
      "code": "002285",
      "name": "世联行"
    },
    {
      "code": "002340",
      "name": "格林美"
    },
    {
      "code": "002642",
      "name": "荣之联"
    },
    {
      "code": "300165",
      "name": "天瑞仪器"
    },
    {
      "code": "603009",
      "name": "北特科技"
    },
    {
      "code": "603701",
      "name": "德宏股份"
    },
    {
      "code": "000716",
      "name": "黑芝麻"
    },
    {
      "code": "002280",
      "name": "联络互动"
    },
    {
      "code": "002286",
      "name": "保龄宝"
    },
    {
      "code": "300058",
      "name": "蓝色光标"
    },
    {
      "code": "300472",
      "name": "新元科技"
    },
    {
      "code": "600079",
      "name": "人福医药"
    },
    {
      "code": "600082",
      "name": "海泰发展"
    },
    {
      "code": "600282",
      "name": "南钢股份"
    },
    {
      "code": "600736",
      "name": "苏州高新"
    },
    {
      "code": "002195",
      "name": "二三四五"
    },
    {
      "code": "002702",
      "name": "海欣食品"
    },
    {
      "code": "300259",
      "name": "新天科技"
    },
    {
      "code": "600410",
      "name": "华胜天成"
    },
    {
      "code": "600805",
      "name": "悦达投资"
    },
    {
      "code": "600981",
      "name": "汇鸿集团"
    },
    {
      "code": "000551",
      "name": "创元科技"
    },
    {
      "code": "000917",
      "name": "电广传媒"
    },
    {
      "code": "000938",
      "name": "紫光股份"
    },
    {
      "code": "002437",
      "name": "誉衡药业"
    },
    {
      "code": "002622",
      "name": "融钰集团"
    },
    {
      "code": "300035",
      "name": "中科电气"
    },
    {
      "code": "300456",
      "name": "耐威科技"
    },
    {
      "code": "600475",
      "name": "华光股份"
    },
    {
      "code": "600571",
      "name": "信雅达"
    },
    {
      "code": "000507",
      "name": "珠海港"
    },
    {
      "code": "300437",
      "name": "清水源"
    },
    {
      "code": "600635",
      "name": "大众公用"
    },
    {
      "code": "600884",
      "name": "杉杉股份"
    },
    {
      "code": "002157",
      "name": "正邦科技"
    },
    {
      "code": "300018",
      "name": "中元股份"
    },
    {
      "code": "600862",
      "name": "中航高科"
    },
    {
      "code": "000836",
      "name": "富通鑫茂"
    },
    {
      "code": "300231",
      "name": "银信科技"
    },
    {
      "code": "300301",
      "name": "长方集团"
    },
    {
      "code": "600770",
      "name": "综艺股份"
    },
    {
      "code": "000027",
      "name": "深圳能源"
    },
    {
      "code": "002129",
      "name": "中环股份"
    },
    {
      "code": "600851",
      "name": "海欣股份"
    },
    {
      "code": "000998",
      "name": "隆平高科"
    },
    {
      "code": "002004",
      "name": "华邦健康"
    },
    {
      "code": "002076",
      "name": "雪莱特"
    },
    {
      "code": "002353",
      "name": "杰瑞股份"
    },
    {
      "code": "002555",
      "name": "三七互娱"
    },
    {
      "code": "300088",
      "name": "长信科技"
    },
    {
      "code": "002054",
      "name": "德美化工"
    },
    {
      "code": "000513",
      "name": "丽珠集团"
    },
    {
      "code": "300046",
      "name": "台基股份"
    },
    {
      "code": "000997",
      "name": "新大陆"
    },
    {
      "code": "600373",
      "name": "中文传媒"
    },
    {
      "code": "600525",
      "name": "长园集团"
    },
    {
      "code": "002451",
      "name": "摩恩电气"
    },
    {
      "code": "603330",
      "name": "上海天洋"
    },
    {
      "code": "300084",
      "name": "海默科技"
    },
    {
      "code": "300313",
      "name": "天山生物"
    },
    {
      "code": "600783",
      "name": "鲁信创投"
    },
    {
      "code": "000786",
      "name": "北新建材"
    },
    {
      "code": "002730",
      "name": "电光科技"
    },
    {
      "code": "000532",
      "name": "华金资本"
    },
    {
      "code": "002491",
      "name": "通鼎互联"
    },
    {
      "code": "300251",
      "name": "光线传媒"
    },
    {
      "code": "002098",
      "name": "浔兴股份"
    },
    {
      "code": "002376",
      "name": "新北洋"
    },
    {
      "code": "600588",
      "name": "用友网络"
    },
    {
      "code": "300271",
      "name": "华宇软件"
    },
    {
      "code": "002038",
      "name": "双鹭药业"
    },
    {
      "code": "000661",
      "name": "长春高新"
    },
    {
      "code": "603019",
      "name": "中科曙光"
    }
  ]
}