{
  "type": "gn",
  "code": "885749",
  "name": "蚂蚁金服概念",
  "stocks": [
    {
      "code": "603776",
      "name": "永安行"
    },
    {
      "code": "002208",
      "name": "合肥城建"
    },
    {
      "code": "600895",
      "name": "张江高科"
    },
    {
      "code": "300645",
      "name": "正元智慧"
    },
    {
      "code": "300451",
      "name": "创业软件"
    },
    {
      "code": "600728",
      "name": "佳都科技"
    },
    {
      "code": "300253",
      "name": "卫宁健康"
    },
    {
      "code": "000848",
      "name": "承德露露"
    },
    {
      "code": "300096",
      "name": "易联众"
    },
    {
      "code": "600371",
      "name": "万向德农"
    },
    {
      "code": "300682",
      "name": "朗新科技"
    },
    {
      "code": "600015",
      "name": "华夏银行"
    },
    {
      "code": "002029",
      "name": "七匹狼"
    },
    {
      "code": "600229",
      "name": "城市传媒"
    },
    {
      "code": "002515",
      "name": "金字火腿"
    },
    {
      "code": "002117",
      "name": "东港股份"
    },
    {
      "code": "002609",
      "name": "捷顺科技"
    },
    {
      "code": "601216",
      "name": "君正集团"
    },
    {
      "code": "600797",
      "name": "浙大网新"
    },
    {
      "code": "600834",
      "name": "申通地铁"
    },
    {
      "code": "600082",
      "name": "海泰发展"
    },
    {
      "code": "600606",
      "name": "绿地控股"
    },
    {
      "code": "600981",
      "name": "汇鸿集团"
    },
    {
      "code": "300465",
      "name": "高伟达"
    },
    {
      "code": "000665",
      "name": "湖北广电"
    },
    {
      "code": "300339",
      "name": "润和软件"
    },
    {
      "code": "600380",
      "name": "健康元"
    },
    {
      "code": "600476",
      "name": "湘邮科技"
    },
    {
      "code": "600570",
      "name": "恒生电子"
    }
  ]
}